src/server/__init__.py
src/server/__main__.py
src/server/cli.py
src/server/keep_api.py
google_keep_mcp-1.0.2.dist-info/METADATA
google_keep_mcp-1.0.2.dist-info/WHEEL
google_keep_mcp-1.0.2.dist-info/entry_points.txt
google_keep_mcp-1.0.2.dist-info/licenses/LICENSE
google_keep_mcp-1.0.2.dist-info/RECORD
