Metadata-Version: 2.4
Name: google-keep-mcp
Version: 1.0.2
Summary: MCP Server for Google Keep
Project-URL: Homepage, https://github.com/davenicoll/google-keep-mcp
Project-URL: Repository, https://github.com/davenicoll/google-keep-mcp
Author-email: Dave Nicoll <lewkyuqtd@relay.firefox.com>
License: MIT License
License-File: LICENSE
Classifier: Development Status :: 5 - Production/Stable
Classifier: Environment :: Console
Classifier: Intended Audience :: End Users/Desktop
Classifier: License :: OSI Approved :: MIT License
Classifier: Programming Language :: Python :: 3
Classifier: Programming Language :: Python :: 3.12
Classifier: Topic :: Utilities
Requires-Python: >=3.12.11
Requires-Dist: gkeepapi>=0.16.0
Requires-Dist: mcp[cli]
Requires-Dist: python-dotenv
